{
  "Water": {
    "name": "Water",
    "quantity": 38940.0,
    "unit": "ml"
  },
  "Matcha Powder": {
    "name": "Matcha Powder",
    "quantity": 490.0,
    "unit": "g"
  },
  "Vanilla Syrup": {
    "name": "Vanilla Syrup",
    "quantity": 2000.0,
    "unit": "ml"
  },
  "Coffee Beans": {
    "name": "Coffee Beans",
    "quantity": 4460.0,
    "unit": "g"
  },
  "Caramel Syrup": {
    "name": "Caramel Syrup",
    "quantity": 2000.0,
    "unit": "ml"
  },
  "Chocolate Syrup": {
    "name": "Chocolate Syrup",
    "quantity": 2000.0,
    "unit": "ml"
  },
  "Milk": {
    "name": "Milk",
    "quantity": 7080.0,
    "unit": "ml"
  }
}